codetmpl/__init__.py
codetmpl/get_tmpl.py
codetmpl/pkg_info.py
codetmpl/clitools/__init__.py
codetmpl/clitools/cli.py
codetmpl/code/__init__.py
codetmpl/code/hi.py
codetmpl-0.0.1.6.dist-info/LICENSE
codetmpl-0.0.1.6.dist-info/METADATA
codetmpl-0.0.1.6.dist-info/WHEEL
codetmpl-0.0.1.6.dist-info/entry_points.txt
codetmpl-0.0.1.6.dist-info/top_level.txt
codetmpl-0.0.1.6.dist-info/RECORD
